aefaalgo/__init__.py
aefaalgo/aefa_optimize.py
aefaalgo-0.0.5.dist-info/LICENSE.txt
aefaalgo-0.0.5.dist-info/METADATA
aefaalgo-0.0.5.dist-info/WHEEL
aefaalgo-0.0.5.dist-info/top_level.txt
aefaalgo-0.0.5.dist-info/RECORD
