Metadata-Version: 2.1
Name: aefaalgo
Version: 0.0.5
Summary: Python package for AEFA: Artificial electric field algorithm for global optimization
Home-page: UNKNOWN
Author: Sakshi Bhatia, Anupam Yadav
Author-email: sakshisb@yahoo.com, anupuam@gmail.com
License: MIT
Keywords: Optimization,Soft computing,Artificial intelligence,Electric force
Platform: UNKNOWN
Classifier: Programming Language :: Python :: 3
Classifier: License :: OSI Approved :: MIT License
Classifier: Operating System :: OS Independent
Requires-Python: >=3.6
License-File: LICENSE.txt
Requires-Dist: numpy (>=1.19.5)
Requires-Dist: matplotlib (>=2.2.2)
